[
  {
    "ContainingType": "Program\u002B\u003C\u003Ec",
    "Method": "\u003C\u003CMain\u003E$\u003Eb__0_3",
    "RelativePath": "",
    "HttpMethod": "GET",
    "IsController": false,
    "Order": 0,
    "Parameters": [],
    "ReturnTypes": [
      {
        "Type": "System.String",
        "MediaTypes": [
          "text/plain"
        ],
        "StatusCode": 200
      }
    ]
  },
  {
    "ContainingType": "IdealShop.Controllers.AdminController",
    "Method": "GetAll",
    "RelativePath": "api/Admin",
    "HttpMethod": "GET",
    "IsController": true,
    "Order": 0,
    "Parameters": [],
    "ReturnTypes": []
  },
  {
    "ContainingType": "IdealShop.Controllers.AdminController",
    "Method": "Create",
    "RelativePath": "api/Admin",
    "HttpMethod": "POST",
    "IsController": true,
    "Order": 0,
    "Parameters": [
      {
        "Name": "admin",
        "Type": "IdealShop.Models.Admin",
        "IsRequired": true
      }
    ],
    "ReturnTypes": []
  },
  {
    "ContainingType": "IdealShop.Controllers.AdminController",
    "Method": "GetById",
    "RelativePath": "api/Admin/{id}",
    "HttpMethod": "GET",
    "IsController": true,
    "Order": 0,
    "Parameters": [
      {
        "Name": "id",
        "Type": "System.Int32",
        "IsRequired": true
      }
    ],
    "ReturnTypes": []
  },
  {
    "ContainingType": "IdealShop.Controllers.AdminController",
    "Method": "Update",
    "RelativePath": "api/Admin/{id}",
    "HttpMethod": "PUT",
    "IsController": true,
    "Order": 0,
    "Parameters": [
      {
        "Name": "id",
        "Type": "System.Int32",
        "IsRequired": true
      },
      {
        "Name": "admin",
        "Type": "IdealShop.Models.Admin",
        "IsRequired": true
      }
    ],
    "ReturnTypes": []
  },
  {
    "ContainingType": "IdealShop.Controllers.AdminController",
    "Method": "Delete",
    "RelativePath": "api/Admin/{id}",
    "HttpMethod": "DELETE",
    "IsController": true,
    "Order": 0,
    "Parameters": [
      {
        "Name": "id",
        "Type": "System.Int32",
        "IsRequired": true
      }
    ],
    "ReturnTypes": []
  },
  {
    "ContainingType": "IdealShop.Controllers.AdminController",
    "Method": "Login",
    "RelativePath": "api/Admin/login",
    "HttpMethod": "POST",
    "IsController": true,
    "Order": 0,
    "Parameters": [
      {
        "Name": "request",
        "Type": "IdealShop.Controllers.AdminController\u002BLoginRequest",
        "IsRequired": true
      }
    ],
    "ReturnTypes": []
  },
  {
    "ContainingType": "IdealShop.Controllers.AdminController",
    "Method": "Logout",
    "RelativePath": "api/Admin/logout",
    "HttpMethod": "POST",
    "IsController": true,
    "Order": 0,
    "Parameters": [],
    "ReturnTypes": []
  },
  {
    "ContainingType": "IdealShop.Controllers.ProductsController",
    "Method": "GetAll",
    "RelativePath": "api/Products",
    "HttpMethod": "GET",
    "IsController": true,
    "Order": 0,
    "Parameters": [],
    "ReturnTypes": []
  },
  {
    "ContainingType": "IdealShop.Controllers.ProductsController",
    "Method": "Create",
    "RelativePath": "api/Products",
    "HttpMethod": "POST",
    "IsController": true,
    "Order": 0,
    "Parameters": [
      {
        "Name": "Id",
        "Type": "System.Int32",
        "IsRequired": false
      },
      {
        "Name": "Name",
        "Type": "System.String",
        "IsRequired": false
      },
      {
        "Name": "ProductCategoryId",
        "Type": "System.Int32",
        "IsRequired": false
      },
      {
        "Name": "Price",
        "Type": "System.Decimal",
        "IsRequired": false
      },
      {
        "Name": "Stock",
        "Type": "System.Int32",
        "IsRequired": false
      },
      {
        "Name": "ImageUrl",
        "Type": "System.String",
        "IsRequired": false
      },
      {
        "Name": "ImageFile",
        "Type": "Microsoft.AspNetCore.Http.IFormFile",
        "IsRequired": false
      },
      {
        "Name": "ProductCategory.Id",
        "Type": "System.Int32",
        "IsRequired": false
      },
      {
        "Name": "ProductCategory.Name",
        "Type": "System.String",
        "IsRequired": false
      },
      {
        "Name": "ProductCategory.Products",
        "Type": "System.Collections.Generic.List\u00601[[IdealShop.Models.Product, IdealShop, Version=1.0.0.0, Culture=neutral, PublicKeyToken=null]]",
        "IsRequired": false
      }
    ],
    "ReturnTypes": []
  },
  {
    "ContainingType": "IdealShop.Controllers.ProductsController",
    "Method": "Get",
    "RelativePath": "api/Products/{id}",
    "HttpMethod": "GET",
    "IsController": true,
    "Order": 0,
    "Parameters": [
      {
        "Name": "id",
        "Type": "System.Int32",
        "IsRequired": true
      }
    ],
    "ReturnTypes": []
  },
  {
    "ContainingType": "IdealShop.Controllers.ProductsController",
    "Method": "Update",
    "RelativePath": "api/Products/{id}",
    "HttpMethod": "PUT",
    "IsController": true,
    "Order": 0,
    "Parameters": [
      {
        "Name": "id",
        "Type": "System.Int32",
        "IsRequired": true
      },
      {
        "Name": "product",
        "Type": "IdealShop.Models.Product",
        "IsRequired": true
      }
    ],
    "ReturnTypes": []
  },
  {
    "ContainingType": "IdealShop.Controllers.ProductsController",
    "Method": "Delete",
    "RelativePath": "api/Products/{id}",
    "HttpMethod": "DELETE",
    "IsController": true,
    "Order": 0,
    "Parameters": [
      {
        "Name": "id",
        "Type": "System.Int32",
        "IsRequired": true
      }
    ],
    "ReturnTypes": []
  },
  {
    "ContainingType": "IdealShop.Controllers.ProductsController",
    "Method": "GetByCategory",
    "RelativePath": "api/Products/ByCategory/{categoryId}",
    "HttpMethod": "GET",
    "IsController": true,
    "Order": 0,
    "Parameters": [
      {
        "Name": "categoryId",
        "Type": "System.Int32",
        "IsRequired": true
      }
    ],
    "ReturnTypes": []
  }
]